[{"arguments":["clang","-Wno-documentation-unknown-command","-Wno-unknown-warning-option","-Wno-unknown-pragmas","-nostdinc","-nostdinc++","-g","-std=gnu++1z","-Wall","-Wextra","-Wextra","-fexceptions","-mthreads","-fsyntax-only","-m64","--target=x86_64-w64-mingw32","-DUNICODE","-D_UNICODE","-DWIN32","-DMINGW_HAS_SECURE_API","-DQT_QML_DEBUG","-DQT_WIDGETS_LIB","-DQT_GUI_LIB","-DQT_CORE_LIB","-DQT_NEEDS_QMAIN","-DQ_CREATOR_RUN","-IE:\\Qt2\\Tools\\QtCreator\\share\\qtcreator\\cplusplus\\wrappedMingwHeaders","-IE:\\Qt2\\Tools\\QtCreator\\share\\qtcreator\\cplusplus\\wrappedQtHeaders","-IE:\\Qt2\\Tools\\QtCreator\\share\\qtcreator\\cplusplus\\wrappedQtHeaders\\QtCore","-IE:\\git\\2205\\stage2\\regenerate","-IE:\\Qt2\\6.4.3\\mingw_64\\include","-IE:\\Qt2\\6.4.3\\mingw_64\\include\\QtWidgets","-IE:\\Qt2\\6.4.3\\mingw_64\\include\\QtGui","-IE:\\Qt2\\6.4.3\\mingw_64\\include\\QtCore","-IE:\\git\\2205\\stage2\\build-regenerate-Desktop_Qt_6_4_3_MinGW_64_bit-Debug\\debug","-IE:\\git\\2205\\stage2\\build-regenerate-Desktop_Qt_6_4_3_MinGW_64_bit-Debug","-IE:\\Qt2\\6.4.3\\mingw_64\\mkspecs\\win32-g++","-isystem","E:\\Qt2\\Tools\\mingw1120_64\\lib\\gcc\\x86_64-w64-mingw32\\11.2.0\\include\\c++","-isystem","E:\\Qt2\\Tools\\mingw1120_64\\lib\\gcc\\x86_64-w64-mingw32\\11.2.0\\include\\c++\\x86_64-w64-mingw32","-isystem","E:\\Qt2\\Tools\\mingw1120_64\\lib\\gcc\\x86_64-w64-mingw32\\11.2.0\\include\\c++\\backward","-isystem","E:\\Qt2\\Tools\\QtCreator\\bin\\clang\\lib\\clang\\16\\include","-isystem","E:\\Qt2\\Tools\\mingw1120_64\\x86_64-w64-mingw32\\include","-fmessage-length=0","-fdiagnostics-show-note-include-stack","-fretain-comments-from-system-headers","-fmacro-backtrace-limit=0","-ferror-limit=1000","-x","c++","E:\\git\\2205\\stage2\\regenerate\\chess.cpp"],"directory":"E:/git/2205/stage2/build-regenerate-Desktop_Qt_6_4_3_MinGW_64_bit-Debug/.qtc_clangd","file":"E:/git/2205/stage2/regenerate/chess.cpp"},{"arguments":["clang","-Wno-documentation-unknown-command","-Wno-unknown-warning-option","-Wno-unknown-pragmas","-nostdinc","-nostdinc++","-g","-std=gnu++1z","-Wall","-Wextra","-Wextra","-fexceptions","-mthreads","-fsyntax-only","-m64","--target=x86_64-w64-mingw32","-DUNICODE","-D_UNICODE","-DWIN32","-DMINGW_HAS_SECURE_API","-DQT_QML_DEBUG","-DQT_WIDGETS_LIB","-DQT_GUI_LIB","-DQT_CORE_LIB","-DQT_NEEDS_QMAIN","-DQ_CREATOR_RUN","-IE:\\Qt2\\Tools\\QtCreator\\share\\qtcreator\\cplusplus\\wrappedMingwHeaders","-IE:\\Qt2\\Tools\\QtCreator\\share\\qtcreator\\cplusplus\\wrappedQtHeaders","-IE:\\Qt2\\Tools\\QtCreator\\share\\qtcreator\\cplusplus\\wrappedQtHeaders\\QtCore","-IE:\\git\\2205\\stage2\\regenerate","-IE:\\Qt2\\6.4.3\\mingw_64\\include","-IE:\\Qt2\\6.4.3\\mingw_64\\include\\QtWidgets","-IE:\\Qt2\\6.4.3\\mingw_64\\include\\QtGui","-IE:\\Qt2\\6.4.3\\mingw_64\\include\\QtCore","-IE:\\git\\2205\\stage2\\build-regenerate-Desktop_Qt_6_4_3_MinGW_64_bit-Debug\\debug","-IE:\\git\\2205\\stage2\\build-regenerate-Desktop_Qt_6_4_3_MinGW_64_bit-Debug","-IE:\\Qt2\\6.4.3\\mingw_64\\mkspecs\\win32-g++","-isystem","E:\\Qt2\\Tools\\mingw1120_64\\lib\\gcc\\x86_64-w64-mingw32\\11.2.0\\include\\c++","-isystem","E:\\Qt2\\Tools\\mingw1120_64\\lib\\gcc\\x86_64-w64-mingw32\\11.2.0\\include\\c++\\x86_64-w64-mingw32","-isystem","E:\\Qt2\\Tools\\mingw1120_64\\lib\\gcc\\x86_64-w64-mingw32\\11.2.0\\include\\c++\\backward","-isystem","E:\\Qt2\\Tools\\QtCreator\\bin\\clang\\lib\\clang\\16\\include","-isystem","E:\\Qt2\\Tools\\mingw1120_64\\x86_64-w64-mingw32\\include","-fmessage-length=0","-fdiagnostics-show-note-include-stack","-fretain-comments-from-system-headers","-fmacro-backtrace-limit=0","-ferror-limit=1000","-x","c++","E:\\git\\2205\\stage2\\regenerate\\main.cpp"],"directory":"E:/git/2205/stage2/build-regenerate-Desktop_Qt_6_4_3_MinGW_64_bit-Debug/.qtc_clangd","file":"E:/git/2205/stage2/regenerate/main.cpp"},{"arguments":["clang","-Wno-documentation-unknown-command","-Wno-unknown-warning-option","-Wno-unknown-pragmas","-nostdinc","-nostdinc++","-g","-std=gnu++1z","-Wall","-Wextra","-Wextra","-fexceptions","-mthreads","-fsyntax-only","-m64","--target=x86_64-w64-mingw32","-DUNICODE","-D_UNICODE","-DWIN32","-DMINGW_HAS_SECURE_API","-DQT_QML_DEBUG","-DQT_WIDGETS_LIB","-DQT_GUI_LIB","-DQT_CORE_LIB","-DQT_NEEDS_QMAIN","-DQ_CREATOR_RUN","-IE:\\Qt2\\Tools\\QtCreator\\share\\qtcreator\\cplusplus\\wrappedMingwHeaders","-IE:\\Qt2\\Tools\\QtCreator\\share\\qtcreator\\cplusplus\\wrappedQtHeaders","-IE:\\Qt2\\Tools\\QtCreator\\share\\qtcreator\\cplusplus\\wrappedQtHeaders\\QtCore","-IE:\\git\\2205\\stage2\\regenerate","-IE:\\Qt2\\6.4.3\\mingw_64\\include","-IE:\\Qt2\\6.4.3\\mingw_64\\include\\QtWidgets","-IE:\\Qt2\\6.4.3\\mingw_64\\include\\QtGui","-IE:\\Qt2\\6.4.3\\mingw_64\\include\\QtCore","-IE:\\git\\2205\\stage2\\build-regenerate-Desktop_Qt_6_4_3_MinGW_64_bit-Debug\\debug","-IE:\\git\\2205\\stage2\\build-regenerate-Desktop_Qt_6_4_3_MinGW_64_bit-Debug","-IE:\\Qt2\\6.4.3\\mingw_64\\mkspecs\\win32-g++","-isystem","E:\\Qt2\\Tools\\mingw1120_64\\lib\\gcc\\x86_64-w64-mingw32\\11.2.0\\include\\c++","-isystem","E:\\Qt2\\Tools\\mingw1120_64\\lib\\gcc\\x86_64-w64-mingw32\\11.2.0\\include\\c++\\x86_64-w64-mingw32","-isystem","E:\\Qt2\\Tools\\mingw1120_64\\lib\\gcc\\x86_64-w64-mingw32\\11.2.0\\include\\c++\\backward","-isystem","E:\\Qt2\\Tools\\QtCreator\\bin\\clang\\lib\\clang\\16\\include","-isystem","E:\\Qt2\\Tools\\mingw1120_64\\x86_64-w64-mingw32\\include","-fmessage-length=0","-fdiagnostics-show-note-include-stack","-fretain-comments-from-system-headers","-fmacro-backtrace-limit=0","-ferror-limit=1000","-x","c++","E:\\git\\2205\\stage2\\regenerate\\paint.cpp"],"directory":"E:/git/2205/stage2/build-regenerate-Desktop_Qt_6_4_3_MinGW_64_bit-Debug/.qtc_clangd","file":"E:/git/2205/stage2/regenerate/paint.cpp"},{"arguments":["clang","-Wno-documentation-unknown-command","-Wno-unknown-warning-option","-Wno-unknown-pragmas","-nostdinc","-nostdinc++","-g","-std=gnu++1z","-Wall","-Wextra","-Wextra","-fexceptions","-mthreads","-fsyntax-only","-m64","--target=x86_64-w64-mingw32","-DUNICODE","-D_UNICODE","-DWIN32","-DMINGW_HAS_SECURE_API","-DQT_QML_DEBUG","-DQT_WIDGETS_LIB","-DQT_GUI_LIB","-DQT_CORE_LIB","-DQT_NEEDS_QMAIN","-DQ_CREATOR_RUN","-IE:\\Qt2\\Tools\\QtCreator\\share\\qtcreator\\cplusplus\\wrappedMingwHeaders","-IE:\\Qt2\\Tools\\QtCreator\\share\\qtcreator\\cplusplus\\wrappedQtHeaders","-IE:\\Qt2\\Tools\\QtCreator\\share\\qtcreator\\cplusplus\\wrappedQtHeaders\\QtCore","-IE:\\git\\2205\\stage2\\regenerate","-IE:\\Qt2\\6.4.3\\mingw_64\\include","-IE:\\Qt2\\6.4.3\\mingw_64\\include\\QtWidgets","-IE:\\Qt2\\6.4.3\\mingw_64\\include\\QtGui","-IE:\\Qt2\\6.4.3\\mingw_64\\include\\QtCore","-IE:\\git\\2205\\stage2\\build-regenerate-Desktop_Qt_6_4_3_MinGW_64_bit-Debug\\debug","-IE:\\git\\2205\\stage2\\build-regenerate-Desktop_Qt_6_4_3_MinGW_64_bit-Debug","-IE:\\Qt2\\6.4.3\\mingw_64\\mkspecs\\win32-g++","-isystem","E:\\Qt2\\Tools\\mingw1120_64\\lib\\gcc\\x86_64-w64-mingw32\\11.2.0\\include\\c++","-isystem","E:\\Qt2\\Tools\\mingw1120_64\\lib\\gcc\\x86_64-w64-mingw32\\11.2.0\\include\\c++\\x86_64-w64-mingw32","-isystem","E:\\Qt2\\Tools\\mingw1120_64\\lib\\gcc\\x86_64-w64-mingw32\\11.2.0\\include\\c++\\backward","-isystem","E:\\Qt2\\Tools\\QtCreator\\bin\\clang\\lib\\clang\\16\\include","-isystem","E:\\Qt2\\Tools\\mingw1120_64\\x86_64-w64-mingw32\\include","-fmessage-length=0","-fdiagnostics-show-note-include-stack","-fretain-comments-from-system-headers","-fmacro-backtrace-limit=0","-ferror-limit=1000","-x","c++","E:\\git\\2205\\stage2\\regenerate\\rules.cpp"],"directory":"E:/git/2205/stage2/build-regenerate-Desktop_Qt_6_4_3_MinGW_64_bit-Debug/.qtc_clangd","file":"E:/git/2205/stage2/regenerate/rules.cpp"},{"arguments":["clang","-Wno-documentation-unknown-command","-Wno-unknown-warning-option","-Wno-unknown-pragmas","-nostdinc","-nostdinc++","-g","-std=gnu++1z","-Wall","-Wextra","-Wextra","-fexceptions","-mthreads","-fsyntax-only","-m64","--target=x86_64-w64-mingw32","-DUNICODE","-D_UNICODE","-DWIN32","-DMINGW_HAS_SECURE_API","-DQT_QML_DEBUG","-DQT_WIDGETS_LIB","-DQT_GUI_LIB","-DQT_CORE_LIB","-DQT_NEEDS_QMAIN","-DQ_CREATOR_RUN","-IE:\\Qt2\\Tools\\QtCreator\\share\\qtcreator\\cplusplus\\wrappedMingwHeaders","-IE:\\Qt2\\Tools\\QtCreator\\share\\qtcreator\\cplusplus\\wrappedQtHeaders","-IE:\\Qt2\\Tools\\QtCreator\\share\\qtcreator\\cplusplus\\wrappedQtHeaders\\QtCore","-IE:\\git\\2205\\stage2\\regenerate","-IE:\\Qt2\\6.4.3\\mingw_64\\include","-IE:\\Qt2\\6.4.3\\mingw_64\\include\\QtWidgets","-IE:\\Qt2\\6.4.3\\mingw_64\\include\\QtGui","-IE:\\Qt2\\6.4.3\\mingw_64\\include\\QtCore","-IE:\\git\\2205\\stage2\\build-regenerate-Desktop_Qt_6_4_3_MinGW_64_bit-Debug\\debug","-IE:\\git\\2205\\stage2\\build-regenerate-Desktop_Qt_6_4_3_MinGW_64_bit-Debug","-IE:\\Qt2\\6.4.3\\mingw_64\\mkspecs\\win32-g++","-isystem","E:\\Qt2\\Tools\\mingw1120_64\\lib\\gcc\\x86_64-w64-mingw32\\11.2.0\\include\\c++","-isystem","E:\\Qt2\\Tools\\mingw1120_64\\lib\\gcc\\x86_64-w64-mingw32\\11.2.0\\include\\c++\\x86_64-w64-mingw32","-isystem","E:\\Qt2\\Tools\\mingw1120_64\\lib\\gcc\\x86_64-w64-mingw32\\11.2.0\\include\\c++\\backward","-isystem","E:\\Qt2\\Tools\\QtCreator\\bin\\clang\\lib\\clang\\16\\include","-isystem","E:\\Qt2\\Tools\\mingw1120_64\\x86_64-w64-mingw32\\include","-fmessage-length=0","-fdiagnostics-show-note-include-stack","-fretain-comments-from-system-headers","-fmacro-backtrace-limit=0","-ferror-limit=1000","-x","c++","E:\\git\\2205\\stage2\\regenerate\\timer.cpp"],"directory":"E:/git/2205/stage2/build-regenerate-Desktop_Qt_6_4_3_MinGW_64_bit-Debug/.qtc_clangd","file":"E:/git/2205/stage2/regenerate/timer.cpp"},{"arguments":["clang","-Wno-documentation-unknown-command","-Wno-unknown-warning-option","-Wno-unknown-pragmas","-nostdinc","-nostdinc++","-g","-std=gnu++1z","-Wall","-Wextra","-Wextra","-fexceptions","-mthreads","-fsyntax-only","-m64","--target=x86_64-w64-mingw32","-DUNICODE","-D_UNICODE","-DWIN32","-DMINGW_HAS_SECURE_API","-DQT_QML_DEBUG","-DQT_WIDGETS_LIB","-DQT_GUI_LIB","-DQT_CORE_LIB","-DQT_NEEDS_QMAIN","-DQ_CREATOR_RUN","-IE:\\Qt2\\Tools\\QtCreator\\share\\qtcreator\\cplusplus\\wrappedMingwHeaders","-IE:\\Qt2\\Tools\\QtCreator\\share\\qtcreator\\cplusplus\\wrappedQtHeaders","-IE:\\Qt2\\Tools\\QtCreator\\share\\qtcreator\\cplusplus\\wrappedQtHeaders\\QtCore","-IE:\\git\\2205\\stage2\\regenerate","-IE:\\Qt2\\6.4.3\\mingw_64\\include","-IE:\\Qt2\\6.4.3\\mingw_64\\include\\QtWidgets","-IE:\\Qt2\\6.4.3\\mingw_64\\include\\QtGui","-IE:\\Qt2\\6.4.3\\mingw_64\\include\\QtCore","-IE:\\git\\2205\\stage2\\build-regenerate-Desktop_Qt_6_4_3_MinGW_64_bit-Debug\\debug","-IE:\\git\\2205\\stage2\\build-regenerate-Desktop_Qt_6_4_3_MinGW_64_bit-Debug","-IE:\\Qt2\\6.4.3\\mingw_64\\mkspecs\\win32-g++","-isystem","E:\\Qt2\\Tools\\mingw1120_64\\lib\\gcc\\x86_64-w64-mingw32\\11.2.0\\include\\c++","-isystem","E:\\Qt2\\Tools\\mingw1120_64\\lib\\gcc\\x86_64-w64-mingw32\\11.2.0\\include\\c++\\x86_64-w64-mingw32","-isystem","E:\\Qt2\\Tools\\mingw1120_64\\lib\\gcc\\x86_64-w64-mingw32\\11.2.0\\include\\c++\\backward","-isystem","E:\\Qt2\\Tools\\QtCreator\\bin\\clang\\lib\\clang\\16\\include","-isystem","E:\\Qt2\\Tools\\mingw1120_64\\x86_64-w64-mingw32\\include","-fmessage-length=0","-fdiagnostics-show-note-include-stack","-fretain-comments-from-system-headers","-fmacro-backtrace-limit=0","-ferror-limit=1000","-x","c++","E:\\git\\2205\\stage2\\regenerate\\widget.cpp"],"directory":"E:/git/2205/stage2/build-regenerate-Desktop_Qt_6_4_3_MinGW_64_bit-Debug/.qtc_clangd","file":"E:/git/2205/stage2/regenerate/widget.cpp"},{"arguments":["clang","-Wno-documentation-unknown-command","-Wno-unknown-warning-option","-Wno-unknown-pragmas","-nostdinc","-nostdinc++","-g","-std=gnu++1z","-Wall","-Wextra","-Wextra","-fexceptions","-mthreads","-fsyntax-only","-m64","--target=x86_64-w64-mingw32","-DUNICODE","-D_UNICODE","-DWIN32","-DMINGW_HAS_SECURE_API","-DQT_QML_DEBUG","-DQT_WIDGETS_LIB","-DQT_GUI_LIB","-DQT_CORE_LIB","-DQT_NEEDS_QMAIN","-DQ_CREATOR_RUN","-IE:\\Qt2\\Tools\\QtCreator\\share\\qtcreator\\cplusplus\\wrappedMingwHeaders","-IE:\\Qt2\\Tools\\QtCreator\\share\\qtcreator\\cplusplus\\wrappedQtHeaders","-IE:\\Qt2\\Tools\\QtCreator\\share\\qtcreator\\cplusplus\\wrappedQtHeaders\\QtCore","-IE:\\git\\2205\\stage2\\regenerate","-IE:\\Qt2\\6.4.3\\mingw_64\\include","-IE:\\Qt2\\6.4.3\\mingw_64\\include\\QtWidgets","-IE:\\Qt2\\6.4.3\\mingw_64\\include\\QtGui","-IE:\\Qt2\\6.4.3\\mingw_64\\include\\QtCore","-IE:\\git\\2205\\stage2\\build-regenerate-Desktop_Qt_6_4_3_MinGW_64_bit-Debug\\debug","-IE:\\git\\2205\\stage2\\build-regenerate-Desktop_Qt_6_4_3_MinGW_64_bit-Debug","-IE:\\Qt2\\6.4.3\\mingw_64\\mkspecs\\win32-g++","-isystem","E:\\Qt2\\Tools\\mingw1120_64\\lib\\gcc\\x86_64-w64-mingw32\\11.2.0\\include\\c++","-isystem","E:\\Qt2\\Tools\\mingw1120_64\\lib\\gcc\\x86_64-w64-mingw32\\11.2.0\\include\\c++\\x86_64-w64-mingw32","-isystem","E:\\Qt2\\Tools\\mingw1120_64\\lib\\gcc\\x86_64-w64-mingw32\\11.2.0\\include\\c++\\backward","-isystem","E:\\Qt2\\Tools\\QtCreator\\bin\\clang\\lib\\clang\\16\\include","-isystem","E:\\Qt2\\Tools\\mingw1120_64\\x86_64-w64-mingw32\\include","-fmessage-length=0","-fdiagnostics-show-note-include-stack","-fretain-comments-from-system-headers","-fmacro-backtrace-limit=0","-ferror-limit=1000","-x","c++-header","E:\\git\\2205\\stage2\\regenerate\\chess.h"],"directory":"E:/git/2205/stage2/build-regenerate-Desktop_Qt_6_4_3_MinGW_64_bit-Debug/.qtc_clangd","file":"E:/git/2205/stage2/regenerate/chess.h"},{"arguments":["clang","-Wno-documentation-unknown-command","-Wno-unknown-warning-option","-Wno-unknown-pragmas","-nostdinc","-nostdinc++","-g","-std=gnu++1z","-Wall","-Wextra","-Wextra","-fexceptions","-mthreads","-fsyntax-only","-m64","--target=x86_64-w64-mingw32","-DUNICODE","-D_UNICODE","-DWIN32","-DMINGW_HAS_SECURE_API","-DQT_QML_DEBUG","-DQT_WIDGETS_LIB","-DQT_GUI_LIB","-DQT_CORE_LIB","-DQT_NEEDS_QMAIN","-DQ_CREATOR_RUN","-IE:\\Qt2\\Tools\\QtCreator\\share\\qtcreator\\cplusplus\\wrappedMingwHeaders","-IE:\\Qt2\\Tools\\QtCreator\\share\\qtcreator\\cplusplus\\wrappedQtHeaders","-IE:\\Qt2\\Tools\\QtCreator\\share\\qtcreator\\cplusplus\\wrappedQtHeaders\\QtCore","-IE:\\git\\2205\\stage2\\regenerate","-IE:\\Qt2\\6.4.3\\mingw_64\\include","-IE:\\Qt2\\6.4.3\\mingw_64\\include\\QtWidgets","-IE:\\Qt2\\6.4.3\\mingw_64\\include\\QtGui","-IE:\\Qt2\\6.4.3\\mingw_64\\include\\QtCore","-IE:\\git\\2205\\stage2\\build-regenerate-Desktop_Qt_6_4_3_MinGW_64_bit-Debug\\debug","-IE:\\git\\2205\\stage2\\build-regenerate-Desktop_Qt_6_4_3_MinGW_64_bit-Debug","-IE:\\Qt2\\6.4.3\\mingw_64\\mkspecs\\win32-g++","-isystem","E:\\Qt2\\Tools\\mingw1120_64\\lib\\gcc\\x86_64-w64-mingw32\\11.2.0\\include\\c++","-isystem","E:\\Qt2\\Tools\\mingw1120_64\\lib\\gcc\\x86_64-w64-mingw32\\11.2.0\\include\\c++\\x86_64-w64-mingw32","-isystem","E:\\Qt2\\Tools\\mingw1120_64\\lib\\gcc\\x86_64-w64-mingw32\\11.2.0\\include\\c++\\backward","-isystem","E:\\Qt2\\Tools\\QtCreator\\bin\\clang\\lib\\clang\\16\\include","-isystem","E:\\Qt2\\Tools\\mingw1120_64\\x86_64-w64-mingw32\\include","-fmessage-length=0","-fdiagnostics-show-note-include-stack","-fretain-comments-from-system-headers","-fmacro-backtrace-limit=0","-ferror-limit=1000","-x","c++-header","E:\\git\\2205\\stage2\\regenerate\\paint.h"],"directory":"E:/git/2205/stage2/build-regenerate-Desktop_Qt_6_4_3_MinGW_64_bit-Debug/.qtc_clangd","file":"E:/git/2205/stage2/regenerate/paint.h"},{"arguments":["clang","-Wno-documentation-unknown-command","-Wno-unknown-warning-option","-Wno-unknown-pragmas","-nostdinc","-nostdinc++","-g","-std=gnu++1z","-Wall","-Wextra","-Wextra","-fexceptions","-mthreads","-fsyntax-only","-m64","--target=x86_64-w64-mingw32","-DUNICODE","-D_UNICODE","-DWIN32","-DMINGW_HAS_SECURE_API","-DQT_QML_DEBUG","-DQT_WIDGETS_LIB","-DQT_GUI_LIB","-DQT_CORE_LIB","-DQT_NEEDS_QMAIN","-DQ_CREATOR_RUN","-IE:\\Qt2\\Tools\\QtCreator\\share\\qtcreator\\cplusplus\\wrappedMingwHeaders","-IE:\\Qt2\\Tools\\QtCreator\\share\\qtcreator\\cplusplus\\wrappedQtHeaders","-IE:\\Qt2\\Tools\\QtCreator\\share\\qtcreator\\cplusplus\\wrappedQtHeaders\\QtCore","-IE:\\git\\2205\\stage2\\regenerate","-IE:\\Qt2\\6.4.3\\mingw_64\\include","-IE:\\Qt2\\6.4.3\\mingw_64\\include\\QtWidgets","-IE:\\Qt2\\6.4.3\\mingw_64\\include\\QtGui","-IE:\\Qt2\\6.4.3\\mingw_64\\include\\QtCore","-IE:\\git\\2205\\stage2\\build-regenerate-Desktop_Qt_6_4_3_MinGW_64_bit-Debug\\debug","-IE:\\git\\2205\\stage2\\build-regenerate-Desktop_Qt_6_4_3_MinGW_64_bit-Debug","-IE:\\Qt2\\6.4.3\\mingw_64\\mkspecs\\win32-g++","-isystem","E:\\Qt2\\Tools\\mingw1120_64\\lib\\gcc\\x86_64-w64-mingw32\\11.2.0\\include\\c++","-isystem","E:\\Qt2\\Tools\\mingw1120_64\\lib\\gcc\\x86_64-w64-mingw32\\11.2.0\\include\\c++\\x86_64-w64-mingw32","-isystem","E:\\Qt2\\Tools\\mingw1120_64\\lib\\gcc\\x86_64-w64-mingw32\\11.2.0\\include\\c++\\backward","-isystem","E:\\Qt2\\Tools\\QtCreator\\bin\\clang\\lib\\clang\\16\\include","-isystem","E:\\Qt2\\Tools\\mingw1120_64\\x86_64-w64-mingw32\\include","-fmessage-length=0","-fdiagnostics-show-note-include-stack","-fretain-comments-from-system-headers","-fmacro-backtrace-limit=0","-ferror-limit=1000","-x","c++-header","E:\\git\\2205\\stage2\\regenerate\\rules.h"],"directory":"E:/git/2205/stage2/build-regenerate-Desktop_Qt_6_4_3_MinGW_64_bit-Debug/.qtc_clangd","file":"E:/git/2205/stage2/regenerate/rules.h"},{"arguments":["clang","-Wno-documentation-unknown-command","-Wno-unknown-warning-option","-Wno-unknown-pragmas","-nostdinc","-nostdinc++","-g","-std=gnu++1z","-Wall","-Wextra","-Wextra","-fexceptions","-mthreads","-fsyntax-only","-m64","--target=x86_64-w64-mingw32","-DUNICODE","-D_UNICODE","-DWIN32","-DMINGW_HAS_SECURE_API","-DQT_QML_DEBUG","-DQT_WIDGETS_LIB","-DQT_GUI_LIB","-DQT_CORE_LIB","-DQT_NEEDS_QMAIN","-DQ_CREATOR_RUN","-IE:\\Qt2\\Tools\\QtCreator\\share\\qtcreator\\cplusplus\\wrappedMingwHeaders","-IE:\\Qt2\\Tools\\QtCreator\\share\\qtcreator\\cplusplus\\wrappedQtHeaders","-IE:\\Qt2\\Tools\\QtCreator\\share\\qtcreator\\cplusplus\\wrappedQtHeaders\\QtCore","-IE:\\git\\2205\\stage2\\regenerate","-IE:\\Qt2\\6.4.3\\mingw_64\\include","-IE:\\Qt2\\6.4.3\\mingw_64\\include\\QtWidgets","-IE:\\Qt2\\6.4.3\\mingw_64\\include\\QtGui","-IE:\\Qt2\\6.4.3\\mingw_64\\include\\QtCore","-IE:\\git\\2205\\stage2\\build-regenerate-Desktop_Qt_6_4_3_MinGW_64_bit-Debug\\debug","-IE:\\git\\2205\\stage2\\build-regenerate-Desktop_Qt_6_4_3_MinGW_64_bit-Debug","-IE:\\Qt2\\6.4.3\\mingw_64\\mkspecs\\win32-g++","-isystem","E:\\Qt2\\Tools\\mingw1120_64\\lib\\gcc\\x86_64-w64-mingw32\\11.2.0\\include\\c++","-isystem","E:\\Qt2\\Tools\\mingw1120_64\\lib\\gcc\\x86_64-w64-mingw32\\11.2.0\\include\\c++\\x86_64-w64-mingw32","-isystem","E:\\Qt2\\Tools\\mingw1120_64\\lib\\gcc\\x86_64-w64-mingw32\\11.2.0\\include\\c++\\backward","-isystem","E:\\Qt2\\Tools\\QtCreator\\bin\\clang\\lib\\clang\\16\\include","-isystem","E:\\Qt2\\Tools\\mingw1120_64\\x86_64-w64-mingw32\\include","-fmessage-length=0","-fdiagnostics-show-note-include-stack","-fretain-comments-from-system-headers","-fmacro-backtrace-limit=0","-ferror-limit=1000","-x","c++-header","E:\\git\\2205\\stage2\\regenerate\\timer.h"],"directory":"E:/git/2205/stage2/build-regenerate-Desktop_Qt_6_4_3_MinGW_64_bit-Debug/.qtc_clangd","file":"E:/git/2205/stage2/regenerate/timer.h"},{"arguments":["clang","-Wno-documentation-unknown-command","-Wno-unknown-warning-option","-Wno-unknown-pragmas","-nostdinc","-nostdinc++","-g","-std=gnu++1z","-Wall","-Wextra","-Wextra","-fexceptions","-mthreads","-fsyntax-only","-m64","--target=x86_64-w64-mingw32","-DUNICODE","-D_UNICODE","-DWIN32","-DMINGW_HAS_SECURE_API","-DQT_QML_DEBUG","-DQT_WIDGETS_LIB","-DQT_GUI_LIB","-DQT_CORE_LIB","-DQT_NEEDS_QMAIN","-DQ_CREATOR_RUN","-IE:\\Qt2\\Tools\\QtCreator\\share\\qtcreator\\cplusplus\\wrappedMingwHeaders","-IE:\\Qt2\\Tools\\QtCreator\\share\\qtcreator\\cplusplus\\wrappedQtHeaders","-IE:\\Qt2\\Tools\\QtCreator\\share\\qtcreator\\cplusplus\\wrappedQtHeaders\\QtCore","-IE:\\git\\2205\\stage2\\regenerate","-IE:\\Qt2\\6.4.3\\mingw_64\\include","-IE:\\Qt2\\6.4.3\\mingw_64\\include\\QtWidgets","-IE:\\Qt2\\6.4.3\\mingw_64\\include\\QtGui","-IE:\\Qt2\\6.4.3\\mingw_64\\include\\QtCore","-IE:\\git\\2205\\stage2\\build-regenerate-Desktop_Qt_6_4_3_MinGW_64_bit-Debug\\debug","-IE:\\git\\2205\\stage2\\build-regenerate-Desktop_Qt_6_4_3_MinGW_64_bit-Debug","-IE:\\Qt2\\6.4.3\\mingw_64\\mkspecs\\win32-g++","-isystem","E:\\Qt2\\Tools\\mingw1120_64\\lib\\gcc\\x86_64-w64-mingw32\\11.2.0\\include\\c++","-isystem","E:\\Qt2\\Tools\\mingw1120_64\\lib\\gcc\\x86_64-w64-mingw32\\11.2.0\\include\\c++\\x86_64-w64-mingw32","-isystem","E:\\Qt2\\Tools\\mingw1120_64\\lib\\gcc\\x86_64-w64-mingw32\\11.2.0\\include\\c++\\backward","-isystem","E:\\Qt2\\Tools\\QtCreator\\bin\\clang\\lib\\clang\\16\\include","-isystem","E:\\Qt2\\Tools\\mingw1120_64\\x86_64-w64-mingw32\\include","-fmessage-length=0","-fdiagnostics-show-note-include-stack","-fretain-comments-from-system-headers","-fmacro-backtrace-limit=0","-ferror-limit=1000","-x","c++-header","E:\\git\\2205\\stage2\\regenerate\\widget.h"],"directory":"E:/git/2205/stage2/build-regenerate-Desktop_Qt_6_4_3_MinGW_64_bit-Debug/.qtc_clangd","file":"E:/git/2205/stage2/regenerate/widget.h"},{"arguments":["clang","-Wno-documentation-unknown-command","-Wno-unknown-warning-option","-Wno-unknown-pragmas","-nostdinc","-nostdinc++","-g","-std=gnu++1z","-Wall","-Wextra","-Wextra","-fexceptions","-mthreads","-fsyntax-only","-m64","--target=x86_64-w64-mingw32","-DUNICODE","-D_UNICODE","-DWIN32","-DMINGW_HAS_SECURE_API","-DQT_QML_DEBUG","-DQT_WIDGETS_LIB","-DQT_GUI_LIB","-DQT_CORE_LIB","-DQT_NEEDS_QMAIN","-DQ_CREATOR_RUN","-IE:\\Qt2\\Tools\\QtCreator\\share\\qtcreator\\cplusplus\\wrappedMingwHeaders","-IE:\\Qt2\\Tools\\QtCreator\\share\\qtcreator\\cplusplus\\wrappedQtHeaders","-IE:\\Qt2\\Tools\\QtCreator\\share\\qtcreator\\cplusplus\\wrappedQtHeaders\\QtCore","-IE:\\git\\2205\\stage2\\regenerate","-IE:\\Qt2\\6.4.3\\mingw_64\\include","-IE:\\Qt2\\6.4.3\\mingw_64\\include\\QtWidgets","-IE:\\Qt2\\6.4.3\\mingw_64\\include\\QtGui","-IE:\\Qt2\\6.4.3\\mingw_64\\include\\QtCore","-IE:\\git\\2205\\stage2\\build-regenerate-Desktop_Qt_6_4_3_MinGW_64_bit-Debug\\debug","-IE:\\git\\2205\\stage2\\build-regenerate-Desktop_Qt_6_4_3_MinGW_64_bit-Debug","-IE:\\Qt2\\6.4.3\\mingw_64\\mkspecs\\win32-g++","-isystem","E:\\Qt2\\Tools\\mingw1120_64\\lib\\gcc\\x86_64-w64-mingw32\\11.2.0\\include\\c++","-isystem","E:\\Qt2\\Tools\\mingw1120_64\\lib\\gcc\\x86_64-w64-mingw32\\11.2.0\\include\\c++\\x86_64-w64-mingw32","-isystem","E:\\Qt2\\Tools\\mingw1120_64\\lib\\gcc\\x86_64-w64-mingw32\\11.2.0\\include\\c++\\backward","-isystem","E:\\Qt2\\Tools\\QtCreator\\bin\\clang\\lib\\clang\\16\\include","-isystem","E:\\Qt2\\Tools\\mingw1120_64\\x86_64-w64-mingw32\\include","-fmessage-length=0","-fdiagnostics-show-note-include-stack","-fretain-comments-from-system-headers","-fmacro-backtrace-limit=0","-ferror-limit=1000","-x","c++-header","E:\\git\\2205\\stage2\\build-regenerate-Desktop_Qt_6_4_3_MinGW_64_bit-Debug\\ui_widget.h"],"directory":"E:/git/2205/stage2/build-regenerate-Desktop_Qt_6_4_3_MinGW_64_bit-Debug/.qtc_clangd","file":"E:/git/2205/stage2/build-regenerate-Desktop_Qt_6_4_3_MinGW_64_bit-Debug/ui_widget.h"}]